tbparse/__init__.py
tbparse/summary_reader.py
tbparse/version.py
tbparse/tensorflow_stub/__init__.py
tbparse/tensorflow_stub/tensor_util.py
tbparse-0.0.9.dist-info/LICENSE
tbparse-0.0.9.dist-info/METADATA
tbparse-0.0.9.dist-info/WHEEL
tbparse-0.0.9.dist-info/top_level.txt
tbparse-0.0.9.dist-info/RECORD
